axgridcommons/__init__.py
axgridcommons/datafile.py
axgridcommons/lenses.py
axgridcommons/md.py
axgridcommons/path.py
axgridcommons/utils.py
axgridcommons-0.1.3.dist-info/WHEEL
axgridcommons-0.1.3.dist-info/METADATA
axgridcommons-0.1.3.dist-info/RECORD
